deepctl_cmd_update/__init__.py
deepctl_cmd_update/command.py
deepctl_cmd_update/installation.py
deepctl_cmd_update/models.py
deepctl_cmd_update/version_check.py
deepctl_cmd_update-0.1.10.dist-info/METADATA
deepctl_cmd_update-0.1.10.dist-info/WHEEL
deepctl_cmd_update-0.1.10.dist-info/entry_points.txt
deepctl_cmd_update-0.1.10.dist-info/top_level.txt
deepctl_cmd_update-0.1.10.dist-info/RECORD
